secret_manager_ci/__init__.py
secret_manager_ci/cli.py
secret_manager_ci/core.py
secret_manager_ci/main.py
secret_manager_ci/version.py
secret_manager_ci-0.1.1.dist-info/licenses/LICENSE
secret_manager_ci-0.1.1.dist-info/METADATA
secret_manager_ci-0.1.1.dist-info/WHEEL
secret_manager_ci-0.1.1.dist-info/entry_points.txt
secret_manager_ci-0.1.1.dist-info/top_level.txt
secret_manager_ci-0.1.1.dist-info/RECORD
